{
    "version": "6.1.8300",
    "description": "Murex是一个更智能的shell和脚本环境，具有专为可用性、安全性和生产力而设计的高级功能（例如更智能的 DevOps 工具",
    "homepage": "https://murex.rocks/",
    "license": "GPL-2.0",
    "url": "https://nojs.murex.rocks/bin/latest/murex-windows-amd64.exe.zip",
    "hash": "5ecb5a46f181666554797ce6d22bd77db44f9f21caee5d43fdf5bd6d72cc9c93",
    "extract_dir": "bin",
    "bin": [
        [
            "murex-6.1.0-windows-amd64.exe",
            "murex"
        ]
    ],
    "checkver": {
        "github": "https://github.com/lmorg/murex",
        "regex": "v([\\d.]+)"
    },
    "autoupdate": {
        "url": "https://nojs.murex.rocks/bin/latest/murex-windows-amd64.exe.zip"
    }
}
